LICENSE
MANIFEST.in
README.md
interlap.py
setup.py
interlap.egg-info/PKG-INFO
interlap.egg-info/SOURCES.txt
interlap.egg-info/dependency_links.txt
interlap.egg-info/top_level.txt